gecko/__init__.py
gecko_om-0.0.1.dist-info/METADATA
gecko_om-0.0.1.dist-info/WHEEL
gecko_om-0.0.1.dist-info/licenses/LICENSE
gecko_om-0.0.1.dist-info/RECORD
